PyPSocket/__init__.py
PyPSocket/client.py
PyPSocket/exception.py
PyPSocket/server.py
PyPSocket/util.py
PyPSocket/protocols/__init__.py
PyPSocket/protocols/tcp.py
PyPSocket-1.0.0.5.dist-info/LICENSE
PyPSocket-1.0.0.5.dist-info/METADATA
PyPSocket-1.0.0.5.dist-info/WHEEL
PyPSocket-1.0.0.5.dist-info/top_level.txt
PyPSocket-1.0.0.5.dist-info/RECORD
