Metadata-Version: 2.1
Name: PyPSocket
Version: 1.0.0.5
Summary: 소켓을 쉽고 간단하게 사용할 수 있는 모듈
Home-page: https://github.com/Duelit
Author: Duelit
Author-email: jaeyung180@gmail.com
License: UNKNOWN
Platform: UNKNOWN
Classifier: License :: OSI Approved :: MIT License
Requires-Python: >=3
License-File: LICENSE
